temporal/__init__.py
temporal/calendar.py
temporal/duration.py
temporal/exceptions.py
temporal/instant.py
temporal/plain_date.py
temporal/plain_date_time.py
temporal/plain_month_day.py
temporal/plain_time.py
temporal/plain_year_month.py
temporal/timezone.py
temporal/utils.py
temporal/zoned_date_time.py
temporal_python-1.0.20.dist-info/licenses/LICENSE
temporal_python-1.0.20.dist-info/METADATA
temporal_python-1.0.20.dist-info/WHEEL
temporal_python-1.0.20.dist-info/top_level.txt
temporal_python-1.0.20.dist-info/RECORD
