Metadata-Version: 2.4
Name: temporal-python
Version: 1.0.20
Summary: A complete Python port of JavaScript's Temporal API for modern date and time handling
Author-email: Hasanat Kazmi <hasanatkazmi@gmail.com>
Maintainer-email: Hasanat Kazmi <hasanatkazmi@gmail.com>
License: MIT License
Project-URL: Homepage, https://github.com/hasanatkazmi/temporal-python
Project-URL: Documentation, https://github.com/hasanatkazmi/temporal-python#readme
Project-URL: Repository, https://github.com/hasanatkazmi/temporal-python
Project-URL: Bug Tracker, https://github.com/hasanatkazmi/temporal-python/issues
Project-URL: Changelog, https://github.com/hasanatkazmi/temporal-python/blob/main/CHANGELOG.md
Keywords: temporal,date,time,datetime,timezone,duration,calendar,iso8601
Classifier: Development Status :: 5 - Production/Stable
Classifier: Intended Audience :: Developers
Classifier: License :: OSI Approved :: MIT License
Classifier: Operating System :: OS Independent
Classifier: Programming Language :: Python :: 3
Classifier: Programming Language :: Python :: 3.7
Classifier: Programming Language :: Python :: 3.8
Classifier: Programming Language :: Python :: 3.9
Classifier: Programming Language :: Python :: 3.10
Classifier: Programming Language :: Python :: 3.11
Classifier: Programming Language :: Python :: 3.12
Classifier: Topic :: Software Development :: Libraries :: Python Modules
Classifier: Topic :: Utilities
Classifier: Typing :: Typed
Requires-Python: >=3.7
License-File: LICENSE
Requires-Dist: backports.zoneinfo; python_version < "3.9"
Requires-Dist: tzdata; sys_platform == "win32"
Provides-Extra: dev
Requires-Dist: pytest>=6.0; extra == "dev"
Requires-Dist: pytest-cov>=2.0; extra == "dev"
Requires-Dist: black>=22.0; extra == "dev"
Requires-Dist: flake8>=4.0; extra == "dev"
Requires-Dist: mypy>=0.900; extra == "dev"
Requires-Dist: isort>=5.0; extra == "dev"
Requires-Dist: bandit>=1.7; extra == "dev"
Requires-Dist: safety>=2.0; extra == "dev"
Provides-Extra: test
Requires-Dist: pytest>=6.0; extra == "test"
Requires-Dist: pytest-cov>=2.0; extra == "test"
Requires-Dist: pytest-benchmark>=3.0; extra == "test"
Provides-Extra: docs
Requires-Dist: sphinx>=4.0; extra == "docs"
Requires-Dist: sphinx-rtd-theme>=1.0; extra == "docs"
Requires-Dist: sphinx-autodoc-typehints>=1.0; extra == "docs"
Dynamic: license-file
